LICENSE
README.md
pyproject.toml
setup.py
tests/test_binned_statistics.py
tests/test_classifier_as_regressor.py
tests/test_cv.py
tests/test_memoized.py
tests/test_uplift_curves.py
uplift_sklearn.egg-info/PKG-INFO
uplift_sklearn.egg-info/SOURCES.txt
uplift_sklearn.egg-info/dependency_links.txt
uplift_sklearn.egg-info/requires.txt
uplift_sklearn.egg-info/top_level.txt
usklearn/__init__.py
usklearn/base.py
usklearn/pipeline.py
usklearn/classifiers/__init__.py
usklearn/classifiers/classifier_as_regressor.py
usklearn/classifiers/memoized.py
usklearn/datasets/Criteo.py
usklearn/datasets/Hillstrom.py
usklearn/datasets/Information.py
usklearn/datasets/Lalonde.py
usklearn/datasets/Lazada.py
usklearn/datasets/Lenta.py
usklearn/datasets/MarketingAB.py
usklearn/datasets/Megafon.py
usklearn/datasets/Starbucks.py
usklearn/datasets/TelecomChurn.py
usklearn/datasets/__init__.py
usklearn/datasets/base.py
usklearn/datasets/colon.py
usklearn/meta/MLPregressor.py
usklearn/meta/__init__.py
usklearn/meta/base.py
usklearn/meta/multi_model.py
usklearn/meta/nested.py
usklearn/meta/response.py
usklearn/meta/robinson.py
usklearn/meta/s_learner.py
usklearn/meta/target_transform.py
usklearn/meta/x_learner.py
usklearn/metrics/__init__.py
usklearn/metrics/_scorer.py
usklearn/metrics/bins.py
usklearn/metrics/curves.py
usklearn/metrics/regression.py
usklearn/model_selection/__init__.py
usklearn/model_selection/_search.py
usklearn/model_selection/_validation.py
usklearn/preprocessing/__init__.py
usklearn/preprocessing/imbalance.py
usklearn/preprocessing/iptw.py
usklearn/utils/__init__.py
usklearn/utils/array_utils.py
usklearn/utils/metrics.py
usklearn/utils/multi_array.py
usklearn/utils/stats.py
usklearn/utils/validation.py